py4ami/__init__.py
py4ami/ami_config.py
py4ami/ami_demos.py
py4ami/ami_gui.py
py4ami/constants.py
py4ami/dict_lib.py
py4ami/examples.py
py4ami/file_lib.py
py4ami/gutil.py
py4ami/jats_lib.py
py4ami/misc.py
py4ami/pdfreader.py
py4ami/projects.py
py4ami/pyami.ini
py4ami/pyamix.py
py4ami/search_lib.py
py4ami/symbol.py
py4ami/text_lib.py
py4ami/text_xml.py
py4ami/util.py
py4ami/wikimedia.py
py4ami/xml_lib.py
py4ami/resources/SmartStoplist.txt
py4ami/resources/section_templates.json
py4ami-0.0.5.2.dist-info/LICENSE
py4ami-0.0.5.2.dist-info/METADATA
py4ami-0.0.5.2.dist-info/WHEEL
py4ami-0.0.5.2.dist-info/entry_points.txt
py4ami-0.0.5.2.dist-info/top_level.txt
py4ami-0.0.5.2.dist-info/RECORD
